PubUpdater/__init__.py
PubUpdater/pubupd.py
pubupd-1.0.4.dist-info/LICENSE
pubupd-1.0.4.dist-info/METADATA
pubupd-1.0.4.dist-info/WHEEL
pubupd-1.0.4.dist-info/entry_points.txt
pubupd-1.0.4.dist-info/top_level.txt
pubupd-1.0.4.dist-info/RECORD
